Workbook

Sheet Inputs
B1: AAPL 三表联动模型 - 输入数据
B2: 单位：百万美元（股数为百万股，EPS为美元）
B4: [利润表]
B5: 项目 | C5: FY2023 | D5: FY2024 | E5: FY2025
B6: 收入 (Revenue) | C6: 383285 | D6: 391035 | E6: 416178
B7: 营业成本 (COGS) | C7: 214138 | D7: 210352 | E7: 133088
B9: [资产负债表]
B10: 项目 | C10: FY2023 | D10: FY2024 | E10: FY2025
B11: 总资产 (Total Assets) | C11: 352583 | D11: 364980 | E11: 359241
B12: 总负债 (Total Liabilities) | C12: 290437 | D12: 308030 | E12: 285508
B14: [现金流量表]
B15: 项目 | C15: FY2023 | D15: FY2024 | E15: FY2025
B16: 经营现金流 (Operating CF) | C16: 118254 | D16: 111482 | E16: 140222
B17: 资本支出 (CapEx) | C17: -10959 | D17: -9445 | E17: -12720
B19: [其他指标]
B20: 项目 | C20: FY2023 | D20: FY2024 | E20: FY2025
B21: 稀释股数 (百万) | C21: 15813 | D21: 15408 | E21: 14939
B22: 净利润 (Net Income) | C22: 96995 | D22: 93736 | E22: 112010

Sheet 利润表
B1: 苹果公司 (AAPL) - 利润表
B2: 单位：百万美元
B4: 项目 | C4: FY2023 | D4: FY2024 | E4: FY2025 | F4: FY2025同比
B5: 收入 (Revenue) | C5: =Inputs!C6 | D5: =Inputs!D6 | E5: =Inputs!E6 | F5: =(E5-D5)/D5
B6: 营业成本 (COGS) | C6: =Inputs!C7 | D6: =Inputs!D7 | E6: =Inputs!E7 | F6: =(E6-D6)/D6
B7: 毛利润 (Gross Profit) | C7: =C5-C6 | D7: =D5-D6 | E7: =E5-E6 | F7: =(E7-D7)/D7
B8: 毛利率 (Gross Margin) | C8: =C7/C5 | D8: =D7/D5 | E8: =E7/E5
B10: 营业利润 (Operating Income) | C10: 114725 | D10: 123487 | E10: 133157 | F10: =(E10-D10)/D10
B11: 营业利润率 (Operating Margin) | C11: =C10/C5 | D11: =D10/D5 | E11: =E10/E5
B13: 净利润 (Net Income) | C13: =Inputs!C22 | D13: =Inputs!D22 | E13: =Inputs!E22 | F13: =(E13-D13)/D13
B14: 净利润率 (Net Margin) | C14: =C13/C5 | D14: =D13/D5 | E14: =E13/E5
B16: 稀释股数 (百万股) | C16: =Inputs!C21 | D16: =Inputs!D21 | E16: =Inputs!E21
B17: 稀释EPS (美元/股) | C17: =C13/C16 | D17: =D13/D16 | E17: =E13/E16 | F17: =(E17-D17)/D17

Sheet 资产负债表
B1: 苹果公司 (AAPL) - 资产负债表
B2: 单位：百万美元
B4: 项目 | C4: FY2023 | D4: FY2024 | E4: FY2025 | F4: FY2025同比
B5: 总资产 (Total Assets) | C5: =Inputs!C11 | D5: =Inputs!D11 | E5: =Inputs!E11 | F5: =(E5-D5)/D5
B6: 总负债 (Total Liabilities) | C6: =Inputs!C12 | D6: =Inputs!D12 | E6: =Inputs!E12 | F6: =(E6-D6)/D6
B7: 股东权益 (Shareholders Equity) | C7: =C5-C6 | D7: =D5-D6 | E7: =E5-E6 | F7: =(E7-D7)/D7
B9: 负债 + 权益（校验） | C9: =C6+C7 | D9: =D6+D7 | E9: =E6+E7
B11: 资产负债率 | C11: =C6/C5 | D11: =D6/D5 | E11: =E6/E5
B12: ROE (净利润/股东权益) | C12: =利润表!C13/C7 | D12: =利润表!D13/D7 | E12: =利润表!E13/E7
B13: ROA (净利润/总资产) | C13: =利润表!C13/C5 | D13: =利润表!D13/D5 | E13: =利润表!E13/E5

Sheet 现金流量表
B1: 苹果公司 (AAPL) - 现金流量表
B2: 单位：百万美元
B4: 项目 | C4: FY2023 | D4: FY2024 | E4: FY2025 | F4: FY2025同比
B5: 经营现金流 (Operating CF) | C5: =Inputs!C16 | D5: =Inputs!D16 | E5: =Inputs!E16 | F5: =(E5-D5)/D5
B6: 资本支出 (CapEx) | C6: =Inputs!C17 | D6: =Inputs!D17 | E6: =Inputs!E17 | F6: =(E6-D6)/D6
B7: 自由现金流 (FCF) | C7: =C5+C6 | D7: =D5+D6 | E7: =E5+E6 | F7: =(E7-D7)/D7
B8: FCF利润率 (FCF/Revenue) | C8: =C7/利润表!C5 | D8: =D7/利润表!D5 | E8: =E7/利润表!E5
B9: CapEx/Revenue | C9: =C6/利润表!C5 | D9: =D6/利润表!D5 | E9: =E6/利润表!E5

Sheet Checks
B1: 苹果公司 (AAPL) - 平衡校验
B2: 所有校验项应为 TRUE（差值为0）
B4: 校验项目 | C4: FY2023 | D4: FY2024 | E4: FY2025 | F4: 通过?
B5: 资产 = 负债 + 权益（差值=0） | C5: =资产负债表!C5-资产负债表!C9 | D5: =资产负债表!D5-资产负债表!D9 | E5: =资产负债表!E5-资产负债表!E9 | F5: =AND(C5=0,D5=0,E5=0)
B6: 毛利润 = 收入 - COGS（差值=0） | C6: =利润表!C7-(利润表!C5-利润表!C6) | D6: =利润表!D7-(利润表!D5-利润表!D6) | E6: =利润表!E7-(利润表!E5-利润表!E6) | F6: =AND(C6=0,D6=0,E6=0)
B7: FCF = 经营CF + CapEx（差值=0） | C7: =现金流量表!C7-(现金流量表!C5+现金流量表!C6) | D7: =现金流量表!D7-(现金流量表!D5+现金流量表!D6) | E7: =现金流量表!E7-(现金流量表!E5+现金流量表!E6) | F7: =AND(C7=0,D7=0,E7=0)
B8: EPS一致性（计算EPS - 公式EPS，应=0） | C8: =利润表!C17-利润表!C13/利润表!C16 | D8: =利润表!D17-利润表!D13/利润表!D16 | E8: =利润表!E17-利润表!E13/利润表!E16 | F8: =AND(ABS(C8)<0.05,ABS(D8)<0.05,ABS(E8)<0.05)
B9: 盈利质量：经营CF/净利润 > 80% | C9: =现金流量表!C5/利润表!C13 | D9: =现金流量表!D5/利润表!D13 | E9: =现金流量表!E5/利润表!E13 | F9: =AND(C9>0.8,D9>0.8,E9>0.8)
B10: 净利润一致性（利润表 = Inputs） | C10: =利润表!C13-Inputs!C22 | D10: =利润表!D13-Inputs!D22 | E10: =利润表!E13-Inputs!E22 | F10: =AND(C10=0,D10=0,E10=0)
